{
  "mentions": [
    {
      "created_at": "Mon Jun 20 14:15:12 +0000 2016",
      "id": 744896383891574800,
      "id_str": "744896383891574784",
      "text": "@rubyunderhood @anton_davydov наконец-то",
      "truncated": false,
      "entities": {
        "hashtags": [],
        "symbols": [],
        "user_mentions": [
          {
            "screen_name": "rubyunderhood",
            "name": "Ruby-разработчик",
            "id": 3341793591,
            "id_str": "3341793591",
            "indices": [
              0,
              14
            ]
          },
          {
            "screen_name": "anton_davydov",
            "name": "Davy Dovanton",
            "id": 539221178,
            "id_str": "539221178",
            "indices": [
              15,
              29
            ]
          }
        ],
        "urls": []
      },
      "source": "<a href=\"http://twitter.com/download/android\" rel=\"nofollow\">Twitter for Android</a>",
      "in_reply_to_status_id": 744856233450971100,
      "in_reply_to_status_id_str": "744856233450971137",
      "in_reply_to_user_id": 3341793591,
      "in_reply_to_user_id_str": "3341793591",
      "in_reply_to_screen_name": "rubyunderhood",
      "user": {
        "id": 77381915,
        "id_str": "77381915"
      },
      "geo": null,
      "coordinates": null,
      "place": null,
      "contributors": null,
      "is_quote_status": false,
      "retweet_count": 0,
      "favorite_count": 0,
      "favorited": false,
      "retweeted": false,
      "lang": "ru"
    },
    {
      "created_at": "Tue Jun 21 01:21:57 +0000 2016",
      "id": 745064177778098200,
      "id_str": "745064177778098176",
      "text": "@anton_davydov взял с собой два макбука",
      "truncated": false,
      "entities": {
        "hashtags": [],
        "symbols": [],
        "user_mentions": [
          {
            "screen_name": "anton_davydov",
            "name": "Davy Dovanton",
            "id": 539221178,
            "id_str": "539221178",
            "indices": [
              0,
              14
            ]
          }
        ],
        "urls": []
      },
      "source": "<a href=\"http://twitter.com\" rel=\"nofollow\">Twitter Web Client</a>",
      "in_reply_to_status_id": 745063987339923500,
      "in_reply_to_status_id_str": "745063987339923456",
      "in_reply_to_user_id": 539221178,
      "in_reply_to_user_id_str": "539221178",
      "in_reply_to_screen_name": "anton_davydov",
      "user": {
        "id": 287242565,
        "id_str": "287242565"
      },
      "geo": null,
      "coordinates": null,
      "place": null,
      "contributors": null,
      "is_quote_status": false,
      "retweet_count": 0,
      "favorite_count": 0,
      "favorited": false,
      "retweeted": false,
      "lang": "ru"
    },
    {
      "created_at": "Tue Jun 21 12:41:49 +0000 2016",
      "id": 745235271457767400,
      "id_str": "745235271457767424",
      "text": "@anton_davydov насущный вопрос: как в отеле с розетками? Зашёл сейчас в два магазина и там нет переходников ( У тебя же тоже европлаг?",
      "truncated": false,
      "entities": {
        "hashtags": [],
        "symbols": [],
        "user_mentions": [
          {
            "screen_name": "anton_davydov",
            "name": "Davy Dovanton",
            "id": 539221178,
            "id_str": "539221178",
            "indices": [
              0,
              14
            ]
          }
        ],
        "urls": []
      },
      "source": "<a href=\"http://twitter.com/download/iphone\" rel=\"nofollow\">Twitter for iPhone</a>",
      "in_reply_to_status_id": 745126562907856900,
      "in_reply_to_status_id_str": "745126562907856896",
      "in_reply_to_user_id": 539221178,
      "in_reply_to_user_id_str": "539221178",
      "in_reply_to_screen_name": "anton_davydov",
      "user": {
        "id": 10383842,
        "id_str": "10383842"
      },
      "geo": null,
      "coordinates": null,
      "place": null,
      "contributors": null,
      "is_quote_status": false,
      "retweet_count": 0,
      "favorite_count": 0,
      "favorited": false,
      "retweeted": false,
      "lang": "ru"
    },
    {
      "created_at": "Wed Jun 22 07:57:38 +0000 2016",
      "id": 745526145538359300,
      "id_str": "745526145538359296",
      "text": "@anton_davydov да, давай, а то я немного притомился сегодня идти",
      "truncated": false,
      "entities": {
        "hashtags": [],
        "symbols": [],
        "user_mentions": [
          {
            "screen_name": "anton_davydov",
            "name": "Davy Dovanton",
            "id": 539221178,
            "id_str": "539221178",
            "indices": [
              0,
              14
            ]
          }
        ],
        "urls": []
      },
      "source": "<a href=\"http://twitter.com\" rel=\"nofollow\">Twitter Web Client</a>",
      "in_reply_to_status_id": 745494617349447700,
      "in_reply_to_status_id_str": "745494617349447680",
      "in_reply_to_user_id": 539221178,
      "in_reply_to_user_id_str": "539221178",
      "in_reply_to_screen_name": "anton_davydov",
      "user": {
        "id": 10383842,
        "id_str": "10383842"
      },
      "geo": null,
      "coordinates": null,
      "place": {
        "id": "58a4c3a0d54e1400",
        "url": "https://api.twitter.com/1.1/geo/id/58a4c3a0d54e1400.json",
        "place_type": "admin",
        "name": "中区",
        "full_name": "中区, 新加坡",
        "country_code": "SG",
        "country": "新加坡",
        "contained_within": [],
        "bounding_box": {
          "type": "Polygon",
          "coordinates": [
            [
              [
                103.749959507073,
                1.2123138339349
              ],
              [
                103.918426999964,
                1.2123138339349
              ],
              [
                103.918426999964,
                1.36874499902569
              ],
              [
                103.749959507073,
                1.36874499902569
              ]
            ]
          ]
        },
        "attributes": {}
      },
      "contributors": null,
      "is_quote_status": false,
      "retweet_count": 0,
      "favorite_count": 0,
      "favorited": false,
      "retweeted": false,
      "lang": "ru"
    },
    {
      "created_at": "Wed Jun 22 08:21:48 +0000 2016",
      "id": 745532226431914000,
      "id_str": "745532226431913987",
      "text": "@anton_davydov а где такой?",
      "truncated": false,
      "entities": {
        "hashtags": [],
        "symbols": [],
        "user_mentions": [
          {
            "screen_name": "anton_davydov",
            "name": "Davy Dovanton",
            "id": 539221178,
            "id_str": "539221178",
            "indices": [
              0,
              14
            ]
          }
        ],
        "urls": []
      },
      "source": "<a href=\"http://twitter.com/download/android\" rel=\"nofollow\">Twitter for Android</a>",
      "in_reply_to_status_id": 745524768170868700,
      "in_reply_to_status_id_str": "745524768170868736",
      "in_reply_to_user_id": 539221178,
      "in_reply_to_user_id_str": "539221178",
      "in_reply_to_screen_name": "anton_davydov",
      "user": {
        "id": 62229769,
        "id_str": "62229769"
      },
      "geo": null,
      "coordinates": null,
      "place": null,
      "contributors": null,
      "is_quote_status": false,
      "retweet_count": 0,
      "favorite_count": 0,
      "favorited": false,
      "retweeted": false,
      "lang": "ru"
    },
    {
      "created_at": "Wed Jun 22 08:56:50 +0000 2016",
      "id": 745541040392667100,
      "id_str": "745541040392667137",
      "text": "@anton_davydov 👌",
      "truncated": false,
      "entities": {
        "hashtags": [],
        "symbols": [],
        "user_mentions": [
          {
            "screen_name": "anton_davydov",
            "name": "Davy Dovanton",
            "id": 539221178,
            "id_str": "539221178",
            "indices": [
              0,
              14
            ]
          }
        ],
        "urls": []
      },
      "source": "<a href=\"http://twitter.com/download/iphone\" rel=\"nofollow\">Twitter for iPhone</a>",
      "in_reply_to_status_id": 745534434049286100,
      "in_reply_to_status_id_str": "745534434049286144",
      "in_reply_to_user_id": 539221178,
      "in_reply_to_user_id_str": "539221178",
      "in_reply_to_screen_name": "anton_davydov",
      "user": {
        "id": 10383842,
        "id_str": "10383842"
      },
      "geo": null,
      "coordinates": null,
      "place": null,
      "contributors": null,
      "is_quote_status": false,
      "retweet_count": 0,
      "favorite_count": 0,
      "favorited": false,
      "retweeted": false,
      "lang": "und"
    },
    {
      "created_at": "Wed Jun 22 15:33:46 +0000 2016",
      "id": 745640934717567000,
      "id_str": "745640934717566978",
      "text": "@anton_davydov да, не вопрос )",
      "truncated": false,
      "entities": {
        "hashtags": [],
        "symbols": [],
        "user_mentions": [
          {
            "screen_name": "anton_davydov",
            "name": "Davy Dovanton",
            "id": 539221178,
            "id_str": "539221178",
            "indices": [
              0,
              14
            ]
          }
        ],
        "urls": []
      },
      "source": "<a href=\"http://twitter.com/download/iphone\" rel=\"nofollow\">Twitter for iPhone</a>",
      "in_reply_to_status_id": 745638676583964700,
      "in_reply_to_status_id_str": "745638676583964672",
      "in_reply_to_user_id": 539221178,
      "in_reply_to_user_id_str": "539221178",
      "in_reply_to_screen_name": "anton_davydov",
      "user": {
        "id": 10383842,
        "id_str": "10383842"
      },
      "geo": null,
      "coordinates": null,
      "place": {
        "id": "58a4c3a0d54e1400",
        "url": "https://api.twitter.com/1.1/geo/id/58a4c3a0d54e1400.json",
        "place_type": "admin",
        "name": "中区",
        "full_name": "中区, 新加坡",
        "country_code": "SG",
        "country": "新加坡",
        "contained_within": [],
        "bounding_box": {
          "type": "Polygon",
          "coordinates": [
            [
              [
                103.749959507073,
                1.2123138339349
              ],
              [
                103.918426999964,
                1.2123138339349
              ],
              [
                103.918426999964,
                1.36874499902569
              ],
              [
                103.749959507073,
                1.36874499902569
              ]
            ]
          ]
        },
        "attributes": {}
      },
      "contributors": null,
      "is_quote_status": false,
      "retweet_count": 0,
      "favorite_count": 0,
      "favorited": false,
      "retweeted": false,
      "lang": "ru"
    },
    {
      "created_at": "Wed Jun 22 15:53:15 +0000 2016",
      "id": 745645838463012900,
      "id_str": "745645838463012864",
      "text": "@anton_davydov @0legLitvin кто тебе виноват х)",
      "truncated": false,
      "entities": {
        "hashtags": [],
        "symbols": [],
        "user_mentions": [
          {
            "screen_name": "anton_davydov",
            "name": "Davy Dovanton",
            "id": 539221178,
            "id_str": "539221178",
            "indices": [
              0,
              14
            ]
          },
          {
            "screen_name": "0legLitvin",
            "name": "Oleg Litvin",
            "id": 355107376,
            "id_str": "355107376",
            "indices": [
              15,
              26
            ]
          }
        ],
        "urls": []
      },
      "source": "<a href=\"https://about.twitter.com/products/tweetdeck\" rel=\"nofollow\">TweetDeck</a>",
      "in_reply_to_status_id": 745644551684005900,
      "in_reply_to_status_id_str": "745644551684005888",
      "in_reply_to_user_id": 539221178,
      "in_reply_to_user_id_str": "539221178",
      "in_reply_to_screen_name": "anton_davydov",
      "user": {
        "id": 141368630,
        "id_str": "141368630"
      },
      "geo": null,
      "coordinates": null,
      "place": null,
      "contributors": null,
      "is_quote_status": false,
      "retweet_count": 0,
      "favorite_count": 0,
      "favorited": false,
      "retweeted": false,
      "lang": "ru"
    },
    {
      "created_at": "Wed Jun 22 15:53:25 +0000 2016",
      "id": 745645878279536600,
      "id_str": "745645878279536641",
      "text": "@anton_davydov @0legLitvin слишком естественно звучит)",
      "truncated": false,
      "entities": {
        "hashtags": [],
        "symbols": [],
        "user_mentions": [
          {
            "screen_name": "anton_davydov",
            "name": "Davy Dovanton",
            "id": 539221178,
            "id_str": "539221178",
            "indices": [
              0,
              14
            ]
          },
          {
            "screen_name": "0legLitvin",
            "name": "Oleg Litvin",
            "id": 355107376,
            "id_str": "355107376",
            "indices": [
              15,
              26
            ]
          }
        ],
        "urls": []
      },
      "source": "<a href=\"https://about.twitter.com/products/tweetdeck\" rel=\"nofollow\">TweetDeck</a>",
      "in_reply_to_status_id": 745644551684005900,
      "in_reply_to_status_id_str": "745644551684005888",
      "in_reply_to_user_id": 539221178,
      "in_reply_to_user_id_str": "539221178",
      "in_reply_to_screen_name": "anton_davydov",
      "user": {
        "id": 141368630,
        "id_str": "141368630"
      },
      "geo": null,
      "coordinates": null,
      "place": null,
      "contributors": null,
      "is_quote_status": false,
      "retweet_count": 0,
      "favorite_count": 0,
      "favorited": false,
      "retweeted": false,
      "lang": "ru"
    },
    {
      "created_at": "Wed Jun 22 16:19:29 +0000 2016",
      "id": 745652439483809800,
      "id_str": "745652439483809793",
      "text": "@anton_davydov @query_string Прийти на конфу и сказать “А вот Антон не встал до сих пор!”. Так постучать? :)",
      "truncated": false,
      "entities": {
        "hashtags": [],
        "symbols": [],
        "user_mentions": [
          {
            "screen_name": "anton_davydov",
            "name": "Davy Dovanton",
            "id": 539221178,
            "id_str": "539221178",
            "indices": [
              0,
              14
            ]
          },
          {
            "screen_name": "query_string",
            "name": "Professor Genki",
            "id": 10383842,
            "id_str": "10383842",
            "indices": [
              15,
              28
            ]
          }
        ],
        "urls": []
      },
      "source": "<a href=\"http://tapbots.com/software/tweetbot/mac\" rel=\"nofollow\">Tweetbot for Mac</a>",
      "in_reply_to_status_id": 745638676583964700,
      "in_reply_to_status_id_str": "745638676583964672",
      "in_reply_to_user_id": 539221178,
      "in_reply_to_user_id_str": "539221178",
      "in_reply_to_screen_name": "anton_davydov",
      "user": {
        "id": 14722814,
        "id_str": "14722814"
      },
      "geo": null,
      "coordinates": null,
      "place": null,
      "contributors": null,
      "is_quote_status": false,
      "retweet_count": 1,
      "favorite_count": 1,
      "favorited": false,
      "retweeted": true,
      "lang": "ru"
    },
    {
      "created_at": "Wed Jun 22 16:21:22 +0000 2016",
      "id": 745652914182488000,
      "id_str": "745652914182488064",
      "text": "@suxxes @anton_davydov ну вот если бы он выступал – я бы так и поступил, а так понт какой? (",
      "truncated": false,
      "entities": {
        "hashtags": [],
        "symbols": [],
        "user_mentions": [
          {
            "screen_name": "suxxes",
            "name": "Father Frodo",
            "id": 14722814,
            "id_str": "14722814",
            "indices": [
              0,
              7
            ]
          },
          {
            "screen_name": "anton_davydov",
            "name": "Davy Dovanton",
            "id": 539221178,
            "id_str": "539221178",
            "indices": [
              8,
              22
            ]
          }
        ],
        "urls": []
      },
      "source": "<a href=\"http://twitter.com\" rel=\"nofollow\">Twitter Web Client</a>",
      "in_reply_to_status_id": 745652439483809800,
      "in_reply_to_status_id_str": "745652439483809793",
      "in_reply_to_user_id": 14722814,
      "in_reply_to_user_id_str": "14722814",
      "in_reply_to_screen_name": "suxxes",
      "user": {
        "id": 10383842,
        "id_str": "10383842"
      },
      "geo": null,
      "coordinates": null,
      "place": null,
      "contributors": null,
      "is_quote_status": false,
      "retweet_count": 0,
      "favorite_count": 0,
      "favorited": false,
      "retweeted": false,
      "lang": "ru"
    },
    {
      "created_at": "Wed Jun 22 16:25:36 +0000 2016",
      "id": 745653978524942300,
      "id_str": "745653978524942336",
      "text": "@anton_davydov @query_string Дык, целый час шутку придумывал. :)",
      "truncated": false,
      "entities": {
        "hashtags": [],
        "symbols": [],
        "user_mentions": [
          {
            "screen_name": "anton_davydov",
            "name": "Davy Dovanton",
            "id": 539221178,
            "id_str": "539221178",
            "indices": [
              0,
              14
            ]
          },
          {
            "screen_name": "query_string",
            "name": "Professor Genki",
            "id": 10383842,
            "id_str": "10383842",
            "indices": [
              15,
              28
            ]
          }
        ],
        "urls": []
      },
      "source": "<a href=\"http://tapbots.com/software/tweetbot/mac\" rel=\"nofollow\">Tweetbot for Mac</a>",
      "in_reply_to_status_id": 745653297541877800,
      "in_reply_to_status_id_str": "745653297541877760",
      "in_reply_to_user_id": 539221178,
      "in_reply_to_user_id_str": "539221178",
      "in_reply_to_screen_name": "anton_davydov",
      "user": {
        "id": 14722814,
        "id_str": "14722814"
      },
      "geo": null,
      "coordinates": null,
      "place": null,
      "contributors": null,
      "is_quote_status": false,
      "retweet_count": 0,
      "favorite_count": 0,
      "favorited": false,
      "retweeted": false,
      "lang": "ru"
    },
    {
      "created_at": "Wed Jun 22 17:18:27 +0000 2016",
      "id": 745667277408833500,
      "id_str": "745667277408833536",
      "text": "@anton_davydov @0legLitvin Я из Москвы, и по началу мне тоже было непросто сопоставить эти две сущности",
      "truncated": false,
      "entities": {
        "hashtags": [],
        "symbols": [],
        "user_mentions": [
          {
            "screen_name": "anton_davydov",
            "name": "Davy Dovanton",
            "id": 539221178,
            "id_str": "539221178",
            "indices": [
              0,
              14
            ]
          },
          {
            "screen_name": "0legLitvin",
            "name": "Oleg Litvin",
            "id": 355107376,
            "id_str": "355107376",
            "indices": [
              15,
              26
            ]
          }
        ],
        "urls": []
      },
      "source": "<a href=\"http://twitter.com/download/android\" rel=\"nofollow\">Twitter for Android</a>",
      "in_reply_to_status_id": 745644551684005900,
      "in_reply_to_status_id_str": "745644551684005888",
      "in_reply_to_user_id": 539221178,
      "in_reply_to_user_id_str": "539221178",
      "in_reply_to_screen_name": "anton_davydov",
      "user": {
        "id": 312906249,
        "id_str": "312906249"
      },
      "geo": null,
      "coordinates": null,
      "place": null,
      "contributors": null,
      "is_quote_status": false,
      "retweet_count": 0,
      "favorite_count": 0,
      "favorited": false,
      "retweeted": false,
      "lang": "ru"
    }
  ]
}
