{
  "username": "fodoj",
  "start": "07 sep 2015",
  "first": "640760805122801664",
  "post": false,
  "tweets": [
    {
      "created_at": "Mon Sep 07 07:12:27 +0000 2015",
      "id": 640784681311563800,
      "id_str": "640784681311563776",
      "text": ". @Shiroginne новый рекорд бреда :)",
      "source": "<a href=\"http://twitter.com\" rel=\"nofollow\">Twitter Web Client</a>",
      "truncated": false,
      "in_reply_to_status_id": 640784148169400300,
      "in_reply_to_status_id_str": "640784148169400320",
      "in_reply_to_user_id": 25733176,
      "in_reply_to_user_id_str": "25733176",
      "in_reply_to_screen_name": "Shiroginne",
      "user": {
        "id": 3341793591,
        "id_str": "3341793591"
      },
      "geo": null,
      "coordinates": null,
      "place": null,
      "contributors": null,
      "is_quote_status": false,
      "retweet_count": 0,
      "favorite_count": 0,
      "entities": {
        "hashtags": [],
        "symbols": [],
        "user_mentions": [
          {
            "screen_name": "Shiroginne",
            "name": "zhIRo9Inn3",
            "id": 25733176,
            "id_str": "25733176",
            "indices": [
              2,
              13
            ]
          }
        ],
        "urls": []
      },
      "favorited": false,
      "retweeted": false,
      "lang": "ru"
    },
    {
      "created_at": "Mon Sep 07 07:12:17 +0000 2015",
      "id": 640784638554845200,
      "id_str": "640784638554845184",
      "text": "RT @Shiroginne: @rubyunderhood да, потому что \"реальные\" задачи уже давно все решены и самое сложное в них - найти нужную библиотеку ;)",
      "source": "<a href=\"http://twitter.com\" rel=\"nofollow\">Twitter Web Client</a>",
      "truncated": false,
      "in_reply_to_status_id": null,
      "in_reply_to_status_id_str": null,
      "in_reply_to_user_id": null,
      "in_reply_to_user_id_str": null,
      "in_reply_to_screen_name": null,
      "user": {
        "id": 3341793591,
        "id_str": "3341793591"
      },
      "geo": null,
      "coordinates": null,
      "place": null,
      "contributors": null,
      "retweeted_status": {
        "created_at": "Mon Sep 07 07:10:20 +0000 2015",
        "id": 640784148169400300,
        "id_str": "640784148169400320",
        "text": "@rubyunderhood да, потому что \"реальные\" задачи уже давно все решены и самое сложное в них - найти нужную библиотеку ;)",
        "source": "<a href=\"http://itunes.apple.com/us/app/twitter/id409789998?mt=12\" rel=\"nofollow\">Twitter for Mac</a>",
        "truncated": false,
        "in_reply_to_status_id": 640783760041082900,
        "in_reply_to_status_id_str": "640783760041082880",
        "in_reply_to_user_id": 3341793591,
        "in_reply_to_user_id_str": "3341793591",
        "in_reply_to_screen_name": "rubyunderhood",
        "user": {
          "id": 25733176,
          "id_str": "25733176"
        },
        "geo": null,
        "coordinates": null,
        "place": null,
        "contributors": null,
        "is_quote_status": false,
        "retweet_count": 1,
        "favorite_count": 0,
        "entities": {
          "hashtags": [],
          "symbols": [],
          "user_mentions": [
            {
              "screen_name": "rubyunderhood",
              "name": "Ruby разработчик",
              "id": 3341793591,
              "id_str": "3341793591",
              "indices": [
                0,
                14
              ]
            }
          ],
          "urls": []
        },
        "favorited": false,
        "retweeted": false,
        "lang": "ru"
      },
      "is_quote_status": false,
      "retweet_count": 1,
      "favorite_count": 0,
      "entities": {
        "hashtags": [],
        "symbols": [],
        "user_mentions": [
          {
            "screen_name": "Shiroginne",
            "name": "zhIRo9Inn3",
            "id": 25733176,
            "id_str": "25733176",
            "indices": [
              3,
              14
            ]
          },
          {
            "screen_name": "rubyunderhood",
            "name": "Ruby разработчик",
            "id": 3341793591,
            "id_str": "3341793591",
            "indices": [
              16,
              30
            ]
          }
        ],
        "urls": []
      },
      "favorited": false,
      "retweeted": false,
      "lang": "ru"
    },
    {
      "created_at": "Mon Sep 07 07:08:54 +0000 2015",
      "id": 640783785144025100,
      "id_str": "640783785144025088",
      "text": "RT @lisovskyvlad: @rubyunderhood интеграция через http с java системой: импорт картинок по запросы. Горжусь тем, что poro, тесты, легко рас…",
      "source": "<a href=\"http://twitter.com\" rel=\"nofollow\">Twitter Web Client</a>",
      "truncated": false,
      "in_reply_to_status_id": null,
      "in_reply_to_status_id_str": null,
      "in_reply_to_user_id": null,
      "in_reply_to_user_id_str": null,
      "in_reply_to_screen_name": null,
      "user": {
        "id": 3341793591,
        "id_str": "3341793591"
      },
      "geo": null,
      "coordinates": null,
      "place": null,
      "contributors": null,
      "retweeted_status": {
        "created_at": "Mon Sep 07 06:50:03 +0000 2015",
        "id": 640779043428810800,
        "id_str": "640779043428810754",
        "text": "@rubyunderhood интеграция через http с java системой: импорт картинок по запросы. Горжусь тем, что poro, тесты, легко расширять, слои.",
        "source": "<a href=\"http://twitter.com/download/iphone\" rel=\"nofollow\">Twitter for iPhone</a>",
        "truncated": false,
        "in_reply_to_status_id": 640762349209653200,
        "in_reply_to_status_id_str": "640762349209653248",
        "in_reply_to_user_id": 3341793591,
        "in_reply_to_user_id_str": "3341793591",
        "in_reply_to_screen_name": "rubyunderhood",
        "user": {
          "id": 87775435,
          "id_str": "87775435"
        },
        "geo": null,
        "coordinates": null,
        "place": null,
        "contributors": null,
        "is_quote_status": false,
        "retweet_count": 1,
        "favorite_count": 0,
        "entities": {
          "hashtags": [],
          "symbols": [],
          "user_mentions": [
            {
              "screen_name": "rubyunderhood",
              "name": "Ruby разработчик",
              "id": 3341793591,
              "id_str": "3341793591",
              "indices": [
                0,
                14
              ]
            }
          ],
          "urls": []
        },
        "favorited": false,
        "retweeted": false,
        "lang": "ru"
      },
      "is_quote_status": false,
      "retweet_count": 1,
      "favorite_count": 0,
      "entities": {
        "hashtags": [],
        "symbols": [],
        "user_mentions": [
          {
            "screen_name": "lisovskyvlad",
            "name": "Влад Лисовский",
            "id": 87775435,
            "id_str": "87775435",
            "indices": [
              3,
              16
            ]
          },
          {
            "screen_name": "rubyunderhood",
            "name": "Ruby разработчик",
            "id": 3341793591,
            "id_str": "3341793591",
            "indices": [
              18,
              32
            ]
          }
        ],
        "urls": []
      },
      "favorited": false,
      "retweeted": false,
      "lang": "ru"
    },
    {
      "created_at": "Mon Sep 07 07:08:48 +0000 2015",
      "id": 640783760041082900,
      "id_str": "640783760041082880",
      "text": ". @Shiroginne самой сложной задачей были синтетические уроки, не решающие реальных проблем? :) ну окей :)",
      "source": "<a href=\"http://twitter.com\" rel=\"nofollow\">Twitter Web Client</a>",
      "truncated": false,
      "in_reply_to_status_id": 640781244972855300,
      "in_reply_to_status_id_str": "640781244972855296",
      "in_reply_to_user_id": 25733176,
      "in_reply_to_user_id_str": "25733176",
      "in_reply_to_screen_name": "Shiroginne",
      "user": {
        "id": 3341793591,
        "id_str": "3341793591"
      },
      "geo": null,
      "coordinates": null,
      "place": null,
      "contributors": null,
      "is_quote_status": false,
      "retweet_count": 0,
      "favorite_count": 0,
      "entities": {
        "hashtags": [],
        "symbols": [],
        "user_mentions": [
          {
            "screen_name": "Shiroginne",
            "name": "zhIRo9Inn3",
            "id": 25733176,
            "id_str": "25733176",
            "indices": [
              2,
              13
            ]
          }
        ],
        "urls": []
      },
      "favorited": false,
      "retweeted": false,
      "lang": "ru"
    },
    {
      "created_at": "Mon Sep 07 06:08:07 +0000 2015",
      "id": 640768489553285100,
      "id_str": "640768489553285120",
      "text": ".@Shiroginne это вот это вот? https://t.co/mfH4zNdQJT",
      "source": "<a href=\"http://twitter.com\" rel=\"nofollow\">Twitter Web Client</a>",
      "truncated": false,
      "in_reply_to_status_id": 640767375596462100,
      "in_reply_to_status_id_str": "640767375596462080",
      "in_reply_to_user_id": 25733176,
      "in_reply_to_user_id_str": "25733176",
      "in_reply_to_screen_name": "Shiroginne",
      "user": {
        "id": 3341793591,
        "id_str": "3341793591"
      },
      "geo": null,
      "coordinates": null,
      "place": null,
      "contributors": null,
      "is_quote_status": false,
      "retweet_count": 0,
      "favorite_count": 1,
      "entities": {
        "hashtags": [],
        "symbols": [],
        "user_mentions": [
          {
            "screen_name": "Shiroginne",
            "name": "zhIRo9Inn3",
            "id": 25733176,
            "id_str": "25733176",
            "indices": [
              1,
              12
            ]
          }
        ],
        "urls": [
          {
            "url": "https://t.co/mfH4zNdQJT",
            "expanded_url": "https://codility.com/programmers/lessons/",
            "display_url": "codility.com/programmers/le…",
            "indices": [
              30,
              53
            ]
          }
        ]
      },
      "favorited": false,
      "retweeted": false,
      "possibly_sensitive": false,
      "lang": "ru"
    },
    {
      "created_at": "Mon Sep 07 06:07:59 +0000 2015",
      "id": 640768455684264000,
      "id_str": "640768455684263936",
      "text": "RT @Shiroginne: @rubyunderhood codility 100/100",
      "source": "<a href=\"http://twitter.com\" rel=\"nofollow\">Twitter Web Client</a>",
      "truncated": false,
      "in_reply_to_status_id": null,
      "in_reply_to_status_id_str": null,
      "in_reply_to_user_id": null,
      "in_reply_to_user_id_str": null,
      "in_reply_to_screen_name": null,
      "user": {
        "id": 3341793591,
        "id_str": "3341793591"
      },
      "geo": null,
      "coordinates": null,
      "place": null,
      "contributors": null,
      "retweeted_status": {
        "created_at": "Mon Sep 07 06:03:41 +0000 2015",
        "id": 640767375596462100,
        "id_str": "640767375596462080",
        "text": "@rubyunderhood codility 100/100",
        "source": "<a href=\"http://tapbots.com/tweetbot\" rel=\"nofollow\">Tweetbot for iΟS</a>",
        "truncated": false,
        "in_reply_to_status_id": 640762349209653200,
        "in_reply_to_status_id_str": "640762349209653248",
        "in_reply_to_user_id": 3341793591,
        "in_reply_to_user_id_str": "3341793591",
        "in_reply_to_screen_name": "rubyunderhood",
        "user": {
          "id": 25733176,
          "id_str": "25733176"
        },
        "geo": null,
        "coordinates": null,
        "place": null,
        "contributors": null,
        "is_quote_status": false,
        "retweet_count": 1,
        "favorite_count": 0,
        "entities": {
          "hashtags": [],
          "symbols": [],
          "user_mentions": [
            {
              "screen_name": "rubyunderhood",
              "name": "Ruby разработчик",
              "id": 3341793591,
              "id_str": "3341793591",
              "indices": [
                0,
                14
              ]
            }
          ],
          "urls": []
        },
        "favorited": false,
        "retweeted": false,
        "lang": "en"
      },
      "is_quote_status": false,
      "retweet_count": 1,
      "favorite_count": 0,
      "entities": {
        "hashtags": [],
        "symbols": [],
        "user_mentions": [
          {
            "screen_name": "Shiroginne",
            "name": "zhIRo9Inn3",
            "id": 25733176,
            "id_str": "25733176",
            "indices": [
              3,
              14
            ]
          },
          {
            "screen_name": "rubyunderhood",
            "name": "Ruby разработчик",
            "id": 3341793591,
            "id_str": "3341793591",
            "indices": [
              16,
              30
            ]
          }
        ],
        "urls": []
      },
      "favorited": false,
      "retweeted": false,
      "lang": "en"
    },
    {
      "created_at": "Mon Sep 07 05:46:41 +0000 2015",
      "id": 640763096051675100,
      "id_str": "640763096051675136",
      "text": ".@ptzn а никто и не говорил что будет легко",
      "source": "<a href=\"http://twitter.com\" rel=\"nofollow\">Twitter Web Client</a>",
      "truncated": false,
      "in_reply_to_status_id": 640762957526384600,
      "in_reply_to_status_id_str": "640762957526384640",
      "in_reply_to_user_id": 8705642,
      "in_reply_to_user_id_str": "8705642",
      "in_reply_to_screen_name": "ptzn",
      "user": {
        "id": 3341793591,
        "id_str": "3341793591"
      },
      "geo": null,
      "coordinates": null,
      "place": null,
      "contributors": null,
      "is_quote_status": false,
      "retweet_count": 0,
      "favorite_count": 0,
      "entities": {
        "hashtags": [],
        "symbols": [],
        "user_mentions": [
          {
            "screen_name": "ptzn",
            "name": "ptzn",
            "id": 8705642,
            "id_str": "8705642",
            "indices": [
              1,
              6
            ]
          }
        ],
        "urls": []
      },
      "favorited": false,
      "retweeted": false,
      "lang": "ru"
    },
    {
      "created_at": "Mon Sep 07 05:46:32 +0000 2015",
      "id": 640763057212387300,
      "id_str": "640763057212387328",
      "text": "RT @ptzn: @rubyunderhood @fodoj максимальные детали в 140 символах? Звучит как челлендж :)",
      "source": "<a href=\"http://twitter.com\" rel=\"nofollow\">Twitter Web Client</a>",
      "truncated": false,
      "in_reply_to_status_id": null,
      "in_reply_to_status_id_str": null,
      "in_reply_to_user_id": null,
      "in_reply_to_user_id_str": null,
      "in_reply_to_screen_name": null,
      "user": {
        "id": 3341793591,
        "id_str": "3341793591"
      },
      "geo": null,
      "coordinates": null,
      "place": null,
      "contributors": null,
      "retweeted_status": {
        "created_at": "Mon Sep 07 05:46:08 +0000 2015",
        "id": 640762957526384600,
        "id_str": "640762957526384640",
        "text": "@rubyunderhood @fodoj максимальные детали в 140 символах? Звучит как челлендж :)",
        "source": "<a href=\"http://itunes.apple.com/us/app/twitter/id409789998?mt=12\" rel=\"nofollow\">Twitter for Mac</a>",
        "truncated": false,
        "in_reply_to_status_id": 640762349209653200,
        "in_reply_to_status_id_str": "640762349209653248",
        "in_reply_to_user_id": 3341793591,
        "in_reply_to_user_id_str": "3341793591",
        "in_reply_to_screen_name": "rubyunderhood",
        "user": {
          "id": 8705642,
          "id_str": "8705642"
        },
        "geo": null,
        "coordinates": null,
        "place": null,
        "contributors": null,
        "is_quote_status": false,
        "retweet_count": 1,
        "favorite_count": 0,
        "entities": {
          "hashtags": [],
          "symbols": [],
          "user_mentions": [
            {
              "screen_name": "rubyunderhood",
              "name": "Ruby разработчик",
              "id": 3341793591,
              "id_str": "3341793591",
              "indices": [
                0,
                14
              ]
            },
            {
              "screen_name": "Fodoj",
              "name": "Kirill Shirinkin",
              "id": 14741065,
              "id_str": "14741065",
              "indices": [
                15,
                21
              ]
            }
          ],
          "urls": []
        },
        "favorited": false,
        "retweeted": false,
        "lang": "ru"
      },
      "is_quote_status": false,
      "retweet_count": 1,
      "favorite_count": 0,
      "entities": {
        "hashtags": [],
        "symbols": [],
        "user_mentions": [
          {
            "screen_name": "ptzn",
            "name": "ptzn",
            "id": 8705642,
            "id_str": "8705642",
            "indices": [
              3,
              8
            ]
          },
          {
            "screen_name": "rubyunderhood",
            "name": "Ruby разработчик",
            "id": 3341793591,
            "id_str": "3341793591",
            "indices": [
              10,
              24
            ]
          },
          {
            "screen_name": "Fodoj",
            "name": "Kirill Shirinkin",
            "id": 14741065,
            "id_str": "14741065",
            "indices": [
              25,
              31
            ]
          }
        ],
        "urls": []
      },
      "favorited": false,
      "retweeted": false,
      "lang": "ru"
    },
    {
      "created_at": "Mon Sep 07 05:43:43 +0000 2015",
      "id": 640762349209653200,
      "id_str": "640762349209653248",
      "text": "Мой любимый вопрос: какой была последняя сложная задача, которую вы решали и решением которой гордитесь? В максимальных деталях, pls.",
      "source": "<a href=\"http://twitter.com\" rel=\"nofollow\">Twitter Web Client</a>",
      "truncated": false,
      "in_reply_to_status_id": null,
      "in_reply_to_status_id_str": null,
      "in_reply_to_user_id": null,
      "in_reply_to_user_id_str": null,
      "in_reply_to_screen_name": null,
      "user": {
        "id": 3341793591,
        "id_str": "3341793591"
      },
      "geo": null,
      "coordinates": null,
      "place": null,
      "contributors": null,
      "is_quote_status": false,
      "retweet_count": 1,
      "favorite_count": 1,
      "entities": {
        "hashtags": [],
        "symbols": [],
        "user_mentions": [],
        "urls": []
      },
      "favorited": false,
      "retweeted": false,
      "lang": "ru"
    },
    {
      "created_at": "Mon Sep 07 05:41:52 +0000 2015",
      "id": 640761884292042800,
      "id_str": "640761884292042752",
      "text": "Ах да, продолжая представляться: обо мне больше на http://t.co/fGhVgwcVx3, mkdev.me и https://t.co/8gBzRxZg8m.",
      "source": "<a href=\"http://twitter.com\" rel=\"nofollow\">Twitter Web Client</a>",
      "truncated": false,
      "in_reply_to_status_id": null,
      "in_reply_to_status_id_str": null,
      "in_reply_to_user_id": null,
      "in_reply_to_user_id_str": null,
      "in_reply_to_screen_name": null,
      "user": {
        "id": 3341793591,
        "id_str": "3341793591"
      },
      "geo": null,
      "coordinates": null,
      "place": null,
      "contributors": null,
      "is_quote_status": false,
      "retweet_count": 1,
      "favorite_count": 0,
      "entities": {
        "hashtags": [],
        "symbols": [],
        "user_mentions": [],
        "urls": [
          {
            "url": "http://t.co/fGhVgwcVx3",
            "expanded_url": "http://fodoj.com",
            "display_url": "fodoj.com",
            "indices": [
              51,
              73
            ]
          },
          {
            "url": "https://t.co/8gBzRxZg8m",
            "expanded_url": "https://de.linkedin.com/in/kshirinkin",
            "display_url": "de.linkedin.com/in/kshirinkin",
            "indices": [
              86,
              109
            ]
          }
        ]
      },
      "favorited": false,
      "retweeted": false,
      "possibly_sensitive": false,
      "lang": "ru"
    },
    {
      "created_at": "Mon Sep 07 05:40:20 +0000 2015",
      "id": 640761497732423700,
      "id_str": "640761497732423680",
      "text": "Следующие 7 дней я буду раздражать вас вопросами и вбрасывать на вентилятор своё мнение о разных вещах.",
      "source": "<a href=\"http://twitter.com\" rel=\"nofollow\">Twitter Web Client</a>",
      "truncated": false,
      "in_reply_to_status_id": null,
      "in_reply_to_status_id_str": null,
      "in_reply_to_user_id": null,
      "in_reply_to_user_id_str": null,
      "in_reply_to_screen_name": null,
      "user": {
        "id": 3341793591,
        "id_str": "3341793591"
      },
      "geo": null,
      "coordinates": null,
      "place": null,
      "contributors": null,
      "is_quote_status": false,
      "retweet_count": 1,
      "favorite_count": 0,
      "entities": {
        "hashtags": [],
        "symbols": [],
        "user_mentions": [],
        "urls": []
      },
      "favorited": false,
      "retweeted": false,
      "lang": "ru"
    },
    {
      "created_at": "Mon Sep 07 05:37:35 +0000 2015",
      "id": 640760805122801700,
      "id_str": "640760805122801664",
      "text": "Йу! Я Кирилл Ширинкин, сертифицированный архитектор, девопс инженер, backend разработчик, технический и не технический автор и ментор.",
      "source": "<a href=\"http://twitter.com\" rel=\"nofollow\">Twitter Web Client</a>",
      "truncated": false,
      "in_reply_to_status_id": null,
      "in_reply_to_status_id_str": null,
      "in_reply_to_user_id": null,
      "in_reply_to_user_id_str": null,
      "in_reply_to_screen_name": null,
      "user": {
        "id": 3341793591,
        "id_str": "3341793591"
      },
      "geo": null,
      "coordinates": null,
      "place": null,
      "contributors": null,
      "is_quote_status": false,
      "retweet_count": 2,
      "favorite_count": 1,
      "entities": {
        "hashtags": [],
        "symbols": [],
        "user_mentions": [],
        "urls": []
      },
      "favorited": false,
      "retweeted": false,
      "lang": "ru"
    }
  ]
}
